ThiagoCalc/ThiagoCalc.py
ThiagoCalc/__init__.py
ThiagoCal-0.3.1.dist-info/METADATA
ThiagoCal-0.3.1.dist-info/WHEEL
ThiagoCal-0.3.1.dist-info/top_level.txt
ThiagoCal-0.3.1.dist-info/RECORD
