Metadata-Version: 2.1
Name: ThiagoCal
Version: 0.3.1
Summary: Calculadora
Home-page: https://github.com/seu_usuario/ThiagoCalc
Author: Thiago
Author-email: seu.email@example.com
Classifier: Programming Language :: Python :: 3
Classifier: License :: OSI Approved :: MIT License
Classifier: Operating System :: OS Independent
Requires-Python: >=3.6
